{
    "price": {
        "current": {
            "datetime": "2022-12-23 00:00:00",
            "count": 120.0,
            "mean": 2958.0,
            "std": 247.74478600284738,
            "min": 2200.0,
            "25%": 2980.0,
            "50%": 2980.0,
            "75%": 2980.0,
            "max": 4380.0
        },
        "summary7Days": {
            "datetime": "2022-12-23 00:00:00",
            "count": -6.0,
            "mean": -10.888888888888687,
            "std": -26.82898469558546,
            "min": 0.0,
            "25%": 0.0,
            "50%": 0.0,
            "75%": 0.0,
            "max": 0.0
        },
        "volatility": {
            "weekly": {
                "min": {
                    "basePrice": 2200.0,
                    "latestPrice": 2200.0,
                    "percent": 0.0
                },
                "50%": {
                    "basePrice": 2980.0,
                    "latestPrice": 2980.0,
                    "percent": 0.0
                }
            },
            "daily": {
                "min": {
                    "basePrice": 2200.0,
                    "latestPrice": 2200.0,
                    "percent": 0.0
                },
                "50%": {
                    "basePrice": 2980.0,
                    "latestPrice": 2980.0,
                    "percent": 0.0
                }
            }
        },
        "weekly": {
            "archive": {
                "count": 7,
                "data": [
                    {
                        "datetime": "2022-12-17 00:00:00",
                        "count": 126.0,
                        "mean": 2968.8888888888887,
                        "std": 274.57377069843284,
                        "min": 2200.0,
                        "25%": 2980.0,
                        "50%": 2980.0,
                        "75%": 2980.0,
                        "max": 4380.0
                    },
                    {
                        "datetime": "2022-12-18 00:00:00",
                        "count": 126.0,
                        "mean": 2968.8888888888887,
                        "std": 274.5737706984328,
                        "min": 2200.0,
                        "25%": 2980.0,
                        "50%": 2980.0,
                        "75%": 2980.0,
                        "max": 4380.0
                    },
                    {
                        "datetime": "2022-12-19 00:00:00",
                        "count": 126.0,
                        "mean": 2968.8888888888887,
                        "std": 274.57377069843284,
                        "min": 2200.0,
                        "25%": 2980.0,
                        "50%": 2980.0,
                        "75%": 2980.0,
                        "max": 4380.0
                    },
                    {
                        "datetime": "2022-12-20 00:00:00",
                        "count": 123.0,
                        "mean": 2970.813008130081,
                        "std": 276.2797153988634,
                        "min": 2200.0,
                        "25%": 2980.0,
                        "50%": 2980.0,
                        "75%": 2980.0,
                        "max": 4380.0
                    },
                    {
                        "datetime": "2022-12-21 00:00:00",
                        "count": 119.0,
                        "mean": 2969.831932773109,
                        "std": 280.8702673962655,
                        "min": 2200.0,
                        "25%": 2980.0,
                        "50%": 2980.0,
                        "75%": 2980.0,
                        "max": 4380.0
                    },
                    {
                        "datetime": "2022-12-22 00:00:00",
                        "count": 119.0,
                        "mean": 2969.5798319327732,
                        "std": 280.87452702013593,
                        "min": 2200.0,
                        "25%": 2980.0,
                        "50%": 2980.0,
                        "75%": 2980.0,
                        "max": 4380.0
                    },
                    {
                        "datetime": "2022-12-23 00:00:00",
                        "count": 120.0,
                        "mean": 2958.0,
                        "std": 247.74478600284738,
                        "min": 2200.0,
                        "25%": 2980.0,
                        "50%": 2980.0,
                        "75%": 2980.0,
                        "max": 4380.0
                    }
                ]
            },
            "diff": {
                "count": 7,
                "data": [
                    {
                        "datetime": "2022-12-17 00:00:00",
                        "count": null,
                        "mean": null,
                        "std": null,
                        "min": null,
                        "25%": null,
                        "50%": null,
                        "75%": null,
                        "max": null
                    },
                    {
                        "datetime": "2022-12-18 00:00:00",
                        "count": 0.0,
                        "mean": 0.0,
                        "std": -5.684341886080802e-14,
                        "min": 0.0,
                        "25%": 0.0,
                        "50%": 0.0,
                        "75%": 0.0,
                        "max": 0.0
                    },
                    {
                        "datetime": "2022-12-19 00:00:00",
                        "count": 0.0,
                        "mean": 0.0,
                        "std": 5.684341886080802e-14,
                        "min": 0.0,
                        "25%": 0.0,
                        "50%": 0.0,
                        "75%": 0.0,
                        "max": 0.0
                    },
                    {
                        "datetime": "2022-12-20 00:00:00",
                        "count": -3.0,
                        "mean": 1.9241192411923294,
                        "std": 1.705944700430564,
                        "min": 0.0,
                        "25%": 0.0,
                        "50%": 0.0,
                        "75%": 0.0,
                        "max": 0.0
                    },
                    {
                        "datetime": "2022-12-21 00:00:00",
                        "count": -4.0,
                        "mean": -0.9810753569718145,
                        "std": 4.590551997402088,
                        "min": 0.0,
                        "25%": 0.0,
                        "50%": 0.0,
                        "75%": 0.0,
                        "max": 0.0
                    },
                    {
                        "datetime": "2022-12-22 00:00:00",
                        "count": 0.0,
                        "mean": -0.25210084033597013,
                        "std": 0.0042596238704391,
                        "min": 0.0,
                        "25%": 0.0,
                        "50%": 0.0,
                        "75%": 0.0,
                        "max": 0.0
                    },
                    {
                        "datetime": "2022-12-23 00:00:00",
                        "count": 1.0,
                        "mean": -11.579831932773232,
                        "std": -33.12974101728855,
                        "min": 0.0,
                        "25%": 0.0,
                        "50%": 0.0,
                        "75%": 0.0,
                        "max": 0.0
                    }
                ]
            }
        },
        "halfYear": {
            "archive": {
                "count": 13,
                "data": [
                    {
                        "datetime": "2022-07-08 00:00:00",
                        "count": 0.0,
                        "mean": 0.0,
                        "std": 0.0,
                        "min": 0.0,
                        "25%": 0.0,
                        "50%": 0.0,
                        "75%": 0.0,
                        "max": 0.0
                    },
                    {
                        "datetime": "2022-07-22 00:00:00",
                        "count": 0.0,
                        "mean": 0.0,
                        "std": 0.0,
                        "min": 0.0,
                        "25%": 0.0,
                        "50%": 0.0,
                        "75%": 0.0,
                        "max": 0.0
                    },
                    {
                        "datetime": "2022-08-05 00:00:00",
                        "count": 0.0,
                        "mean": 0.0,
                        "std": 0.0,
                        "min": 0.0,
                        "25%": 0.0,
                        "50%": 0.0,
                        "75%": 0.0,
                        "max": 0.0
                    },
                    {
                        "datetime": "2022-08-19 00:00:00",
                        "count": 0.0,
                        "mean": 0.0,
                        "std": 0.0,
                        "min": 0.0,
                        "25%": 0.0,
                        "50%": 0.0,
                        "75%": 0.0,
                        "max": 0.0
                    },
                    {
                        "datetime": "2022-09-02 00:00:00",
                        "count": 0.0,
                        "mean": 0.0,
                        "std": 0.0,
                        "min": 0.0,
                        "25%": 0.0,
                        "50%": 0.0,
                        "75%": 0.0,
                        "max": 0.0
                    },
                    {
                        "datetime": "2022-09-16 00:00:00",
                        "count": 43.0,
                        "mean": 3791.4651162790697,
                        "std": 222.7823354582855,
                        "min": 3000.0,
                        "25%": 3780.0,
                        "50%": 3780.0,
                        "75%": 3800.0,
                        "max": 4380.0
                    },
                    {
                        "datetime": "2022-09-30 00:00:00",
                        "count": 66.0,
                        "mean": 3423.439393939394,
                        "std": 256.7232648825087,
                        "min": 2780.0,
                        "25%": 3200.0,
                        "50%": 3480.0,
                        "75%": 3480.0,
                        "max": 4380.0
                    },
                    {
                        "datetime": "2022-10-14 00:00:00",
                        "count": 57.0,
                        "mean": 3382.0,
                        "std": 312.62848787110147,
                        "min": 2780.0,
                        "25%": 3200.0,
                        "50%": 3200.0,
                        "75%": 3480.0,
                        "max": 4380.0
                    },
                    {
                        "datetime": "2022-10-28 00:00:00",
                        "count": 42.0,
                        "mean": 3357.2380952380954,
                        "std": 354.31196186162646,
                        "min": 2310.0,
                        "25%": 3200.0,
                        "50%": 3300.0,
                        "75%": 3480.0,
                        "max": 4380.0
                    },
                    {
                        "datetime": "2022-11-11 00:00:00",
                        "count": 84.0,
                        "mean": 3366.54761904762,
                        "std": 290.93722275539824,
                        "min": 2676.0,
                        "25%": 3200.0,
                        "50%": 3480.0,
                        "75%": 3480.0,
                        "max": 4380.0
                    },
                    {
                        "datetime": "2022-11-25 00:00:00",
                        "count": 104.0,
                        "mean": 2985.576923076923,
                        "std": 281.3070289040588,
                        "min": 2480.0,
                        "25%": 2980.0,
                        "50%": 2980.0,
                        "75%": 2980.0,
                        "max": 4380.0
                    },
                    {
                        "datetime": "2022-12-09 00:00:00",
                        "count": 112.0,
                        "mean": 2970.9821428571427,
                        "std": 287.1260507993293,
                        "min": 2200.0,
                        "25%": 2980.0,
                        "50%": 2980.0,
                        "75%": 2980.0,
                        "max": 4380.0
                    },
                    {
                        "datetime": "2022-12-23 00:00:00",
                        "count": 120.0,
                        "mean": 2958.0,
                        "std": 247.74478600284738,
                        "min": 2200.0,
                        "25%": 2980.0,
                        "50%": 2980.0,
                        "75%": 2980.0,
                        "max": 4380.0
                    }
                ]
            },
            "diff": {
                "count": 13,
                "data": [
                    {
                        "datetime": "2022-07-08 00:00:00",
                        "count": null,
                        "mean": null,
                        "std": null,
                        "min": null,
                        "25%": null,
                        "50%": null,
                        "75%": null,
                        "max": null
                    },
                    {
                        "datetime": "2022-07-22 00:00:00",
                        "count": 0.0,
                        "mean": 0.0,
                        "std": 0.0,
                        "min": 0.0,
                        "25%": 0.0,
                        "50%": 0.0,
                        "75%": 0.0,
                        "max": 0.0
                    },
                    {
                        "datetime": "2022-08-05 00:00:00",
                        "count": 0.0,
                        "mean": 0.0,
                        "std": 0.0,
                        "min": 0.0,
                        "25%": 0.0,
                        "50%": 0.0,
                        "75%": 0.0,
                        "max": 0.0
                    },
                    {
                        "datetime": "2022-08-19 00:00:00",
                        "count": 0.0,
                        "mean": 0.0,
                        "std": 0.0,
                        "min": 0.0,
                        "25%": 0.0,
                        "50%": 0.0,
                        "75%": 0.0,
                        "max": 0.0
                    },
                    {
                        "datetime": "2022-09-02 00:00:00",
                        "count": 0.0,
                        "mean": 0.0,
                        "std": 0.0,
                        "min": 0.0,
                        "25%": 0.0,
                        "50%": 0.0,
                        "75%": 0.0,
                        "max": 0.0
                    },
                    {
                        "datetime": "2022-09-16 00:00:00",
                        "count": 43.0,
                        "mean": 3791.4651162790697,
                        "std": 222.7823354582855,
                        "min": 3000.0,
                        "25%": 3780.0,
                        "50%": 3780.0,
                        "75%": 3800.0,
                        "max": 4380.0
                    },
                    {
                        "datetime": "2022-09-30 00:00:00",
                        "count": 23.0,
                        "mean": -368.02572233967567,
                        "std": 33.940929424223214,
                        "min": -220.0,
                        "25%": -580.0,
                        "50%": -300.0,
                        "75%": -320.0,
                        "max": 0.0
                    },
                    {
                        "datetime": "2022-10-14 00:00:00",
                        "count": -9.0,
                        "mean": -41.439393939393995,
                        "std": 55.905222988592755,
                        "min": 0.0,
                        "25%": 0.0,
                        "50%": -280.0,
                        "75%": 0.0,
                        "max": 0.0
                    },
                    {
                        "datetime": "2022-10-28 00:00:00",
                        "count": -15.0,
                        "mean": -24.76190476190459,
                        "std": 41.68347399052499,
                        "min": -470.0,
                        "25%": 0.0,
                        "50%": 100.0,
                        "75%": 0.0,
                        "max": 0.0
                    },
                    {
                        "datetime": "2022-11-11 00:00:00",
                        "count": 42.0,
                        "mean": 9.309523809524762,
                        "std": -63.37473910622822,
                        "min": 366.0,
                        "25%": 0.0,
                        "50%": 180.0,
                        "75%": 0.0,
                        "max": 0.0
                    },
                    {
                        "datetime": "2022-11-25 00:00:00",
                        "count": 20.0,
                        "mean": -380.9706959706973,
                        "std": -9.630193851339413,
                        "min": -196.0,
                        "25%": -220.0,
                        "50%": -500.0,
                        "75%": -500.0,
                        "max": 0.0
                    },
                    {
                        "datetime": "2022-12-09 00:00:00",
                        "count": 8.0,
                        "mean": -14.594780219780205,
                        "std": 5.819021895270453,
                        "min": -280.0,
                        "25%": 0.0,
                        "50%": 0.0,
                        "75%": 0.0,
                        "max": 0.0
                    },
                    {
                        "datetime": "2022-12-23 00:00:00",
                        "count": 8.0,
                        "mean": -12.982142857142662,
                        "std": -39.3812647964819,
                        "min": 0.0,
                        "25%": 0.0,
                        "50%": 0.0,
                        "75%": 0.0,
                        "max": 0.0
                    }
                ]
            }
        },
        "OneYear": {
            "archive": {
                "count": 0,
                "data": []
            },
            "diff": {
                "count": 0,
                "data": []
            }
        }
    },
    "calc": {
        "latest_date": "2022-12-23 00:00:00",
        "updated_at": "2022-12-23 20:08:40"
    }
}