{
    "price": {
        "current": {
            "datetime": "2022-11-26 00:00:00",
            "count": 578.0,
            "mean": 46.62629757785467,
            "std": 15.005561087965805,
            "min": 20.0,
            "25%": 50.0,
            "50%": 50.0,
            "75%": 50.0,
            "max": 150.0
        },
        "summary7Days": {
            "datetime": "2022-11-26 00:00:00",
            "count": 21.0,
            "mean": 0.12719524392289117,
            "std": -0.2661535825261474,
            "min": 0.0,
            "25%": 0.0,
            "50%": 0.0,
            "75%": 0.0,
            "max": 0.0
        },
        "volatility": {
            "weekly": {
                "min": {
                    "basePrice": 20.0,
                    "latestPrice": 20.0,
                    "percent": 0.0
                },
                "50%": {
                    "basePrice": 50.0,
                    "latestPrice": 50.0,
                    "percent": 0.0
                }
            },
            "daily": {
                "min": {
                    "basePrice": 20.0,
                    "latestPrice": 20.0,
                    "percent": 0.0
                },
                "50%": {
                    "basePrice": 50.0,
                    "latestPrice": 50.0,
                    "percent": 0.0
                }
            }
        },
        "weekly": {
            "archive": {
                "count": 7,
                "data": [
                    {
                        "datetime": "2022-11-20 00:00:00",
                        "count": 557.0,
                        "mean": 46.49910233393178,
                        "std": 15.271714670491953,
                        "min": 20.0,
                        "25%": 50.0,
                        "50%": 50.0,
                        "75%": 50.0,
                        "max": 150.0
                    },
                    {
                        "datetime": "2022-11-21 00:00:00",
                        "count": 557.0,
                        "mean": 46.49910233393178,
                        "std": 15.27171467049195,
                        "min": 20.0,
                        "25%": 50.0,
                        "50%": 50.0,
                        "75%": 50.0,
                        "max": 150.0
                    },
                    {
                        "datetime": "2022-11-22 00:00:00",
                        "count": 557.0,
                        "mean": 46.49910233393178,
                        "std": 15.27171467049195,
                        "min": 20.0,
                        "25%": 50.0,
                        "50%": 50.0,
                        "75%": 50.0,
                        "max": 150.0
                    },
                    {
                        "datetime": "2022-11-23 00:00:00",
                        "count": 557.0,
                        "mean": 46.49910233393178,
                        "std": 15.271714670491953,
                        "min": 20.0,
                        "25%": 50.0,
                        "50%": 50.0,
                        "75%": 50.0,
                        "max": 150.0
                    },
                    {
                        "datetime": "2022-11-24 00:00:00",
                        "count": 553.0,
                        "mean": 46.47377938517179,
                        "std": 15.324028552861748,
                        "min": 20.0,
                        "25%": 50.0,
                        "50%": 50.0,
                        "75%": 50.0,
                        "max": 150.0
                    },
                    {
                        "datetime": "2022-11-25 00:00:00",
                        "count": 553.0,
                        "mean": 46.47377938517179,
                        "std": 15.324028552861748,
                        "min": 20.0,
                        "25%": 50.0,
                        "50%": 50.0,
                        "75%": 50.0,
                        "max": 150.0
                    },
                    {
                        "datetime": "2022-11-26 00:00:00",
                        "count": 578.0,
                        "mean": 46.62629757785467,
                        "std": 15.005561087965805,
                        "min": 20.0,
                        "25%": 50.0,
                        "50%": 50.0,
                        "75%": 50.0,
                        "max": 150.0
                    }
                ]
            },
            "diff": {
                "count": 7,
                "data": [
                    {
                        "datetime": "2022-11-20 00:00:00",
                        "count": null,
                        "mean": null,
                        "std": null,
                        "min": null,
                        "25%": null,
                        "50%": null,
                        "75%": null,
                        "max": null
                    },
                    {
                        "datetime": "2022-11-21 00:00:00",
                        "count": 0.0,
                        "mean": 0.0,
                        "std": -3.552713678800501e-15,
                        "min": 0.0,
                        "25%": 0.0,
                        "50%": 0.0,
                        "75%": 0.0,
                        "max": 0.0
                    },
                    {
                        "datetime": "2022-11-22 00:00:00",
                        "count": 0.0,
                        "mean": 0.0,
                        "std": 0.0,
                        "min": 0.0,
                        "25%": 0.0,
                        "50%": 0.0,
                        "75%": 0.0,
                        "max": 0.0
                    },
                    {
                        "datetime": "2022-11-23 00:00:00",
                        "count": 0.0,
                        "mean": 0.0,
                        "std": 3.552713678800501e-15,
                        "min": 0.0,
                        "25%": 0.0,
                        "50%": 0.0,
                        "75%": 0.0,
                        "max": 0.0
                    },
                    {
                        "datetime": "2022-11-24 00:00:00",
                        "count": -4.0,
                        "mean": -0.025322948759992414,
                        "std": 0.05231388236979484,
                        "min": 0.0,
                        "25%": 0.0,
                        "50%": 0.0,
                        "75%": 0.0,
                        "max": 0.0
                    },
                    {
                        "datetime": "2022-11-25 00:00:00",
                        "count": 0.0,
                        "mean": 0.0,
                        "std": 0.0,
                        "min": 0.0,
                        "25%": 0.0,
                        "50%": 0.0,
                        "75%": 0.0,
                        "max": 0.0
                    },
                    {
                        "datetime": "2022-11-26 00:00:00",
                        "count": 25.0,
                        "mean": 0.15251819268288358,
                        "std": -0.31846746489594224,
                        "min": 0.0,
                        "25%": 0.0,
                        "50%": 0.0,
                        "75%": 0.0,
                        "max": 0.0
                    }
                ]
            }
        },
        "halfYear": {
            "archive": {
                "count": 13,
                "data": [
                    {
                        "datetime": "2022-06-11 00:00:00",
                        "count": 0.0,
                        "mean": 0.0,
                        "std": 0.0,
                        "min": 0.0,
                        "25%": 0.0,
                        "50%": 0.0,
                        "75%": 0.0,
                        "max": 0.0
                    },
                    {
                        "datetime": "2022-06-25 00:00:00",
                        "count": 0.0,
                        "mean": 0.0,
                        "std": 0.0,
                        "min": 0.0,
                        "25%": 0.0,
                        "50%": 0.0,
                        "75%": 0.0,
                        "max": 0.0
                    },
                    {
                        "datetime": "2022-07-09 00:00:00",
                        "count": 0.0,
                        "mean": 0.0,
                        "std": 0.0,
                        "min": 0.0,
                        "25%": 0.0,
                        "50%": 0.0,
                        "75%": 0.0,
                        "max": 0.0
                    },
                    {
                        "datetime": "2022-07-23 00:00:00",
                        "count": 0.0,
                        "mean": 0.0,
                        "std": 0.0,
                        "min": 0.0,
                        "25%": 0.0,
                        "50%": 0.0,
                        "75%": 0.0,
                        "max": 0.0
                    },
                    {
                        "datetime": "2022-08-06 00:00:00",
                        "count": 0.0,
                        "mean": 0.0,
                        "std": 0.0,
                        "min": 0.0,
                        "25%": 0.0,
                        "50%": 0.0,
                        "75%": 0.0,
                        "max": 0.0
                    },
                    {
                        "datetime": "2022-08-20 00:00:00",
                        "count": 0.0,
                        "mean": 0.0,
                        "std": 0.0,
                        "min": 0.0,
                        "25%": 0.0,
                        "50%": 0.0,
                        "75%": 0.0,
                        "max": 0.0
                    },
                    {
                        "datetime": "2022-09-03 00:00:00",
                        "count": 0.0,
                        "mean": 0.0,
                        "std": 0.0,
                        "min": 0.0,
                        "25%": 0.0,
                        "50%": 0.0,
                        "75%": 0.0,
                        "max": 0.0
                    },
                    {
                        "datetime": "2022-09-17 00:00:00",
                        "count": 0.0,
                        "mean": 0.0,
                        "std": 0.0,
                        "min": 0.0,
                        "25%": 0.0,
                        "50%": 0.0,
                        "75%": 0.0,
                        "max": 0.0
                    },
                    {
                        "datetime": "2022-10-01 00:00:00",
                        "count": 0.0,
                        "mean": 0.0,
                        "std": 0.0,
                        "min": 0.0,
                        "25%": 0.0,
                        "50%": 0.0,
                        "75%": 0.0,
                        "max": 0.0
                    },
                    {
                        "datetime": "2022-10-15 00:00:00",
                        "count": 0.0,
                        "mean": 0.0,
                        "std": 0.0,
                        "min": 0.0,
                        "25%": 0.0,
                        "50%": 0.0,
                        "75%": 0.0,
                        "max": 0.0
                    },
                    {
                        "datetime": "2022-10-29 00:00:00",
                        "count": 0.0,
                        "mean": 0.0,
                        "std": 0.0,
                        "min": 0.0,
                        "25%": 0.0,
                        "50%": 0.0,
                        "75%": 0.0,
                        "max": 0.0
                    },
                    {
                        "datetime": "2022-11-12 00:00:00",
                        "count": 573.0,
                        "mean": 46.596858638743456,
                        "std": 15.067672194448376,
                        "min": 20.0,
                        "25%": 50.0,
                        "50%": 50.0,
                        "75%": 50.0,
                        "max": 150.0
                    },
                    {
                        "datetime": "2022-11-26 00:00:00",
                        "count": 578.0,
                        "mean": 46.62629757785467,
                        "std": 15.005561087965805,
                        "min": 20.0,
                        "25%": 50.0,
                        "50%": 50.0,
                        "75%": 50.0,
                        "max": 150.0
                    }
                ]
            },
            "diff": {
                "count": 13,
                "data": [
                    {
                        "datetime": "2022-06-11 00:00:00",
                        "count": null,
                        "mean": null,
                        "std": null,
                        "min": null,
                        "25%": null,
                        "50%": null,
                        "75%": null,
                        "max": null
                    },
                    {
                        "datetime": "2022-06-25 00:00:00",
                        "count": 0.0,
                        "mean": 0.0,
                        "std": 0.0,
                        "min": 0.0,
                        "25%": 0.0,
                        "50%": 0.0,
                        "75%": 0.0,
                        "max": 0.0
                    },
                    {
                        "datetime": "2022-07-09 00:00:00",
                        "count": 0.0,
                        "mean": 0.0,
                        "std": 0.0,
                        "min": 0.0,
                        "25%": 0.0,
                        "50%": 0.0,
                        "75%": 0.0,
                        "max": 0.0
                    },
                    {
                        "datetime": "2022-07-23 00:00:00",
                        "count": 0.0,
                        "mean": 0.0,
                        "std": 0.0,
                        "min": 0.0,
                        "25%": 0.0,
                        "50%": 0.0,
                        "75%": 0.0,
                        "max": 0.0
                    },
                    {
                        "datetime": "2022-08-06 00:00:00",
                        "count": 0.0,
                        "mean": 0.0,
                        "std": 0.0,
                        "min": 0.0,
                        "25%": 0.0,
                        "50%": 0.0,
                        "75%": 0.0,
                        "max": 0.0
                    },
                    {
                        "datetime": "2022-08-20 00:00:00",
                        "count": 0.0,
                        "mean": 0.0,
                        "std": 0.0,
                        "min": 0.0,
                        "25%": 0.0,
                        "50%": 0.0,
                        "75%": 0.0,
                        "max": 0.0
                    },
                    {
                        "datetime": "2022-09-03 00:00:00",
                        "count": 0.0,
                        "mean": 0.0,
                        "std": 0.0,
                        "min": 0.0,
                        "25%": 0.0,
                        "50%": 0.0,
                        "75%": 0.0,
                        "max": 0.0
                    },
                    {
                        "datetime": "2022-09-17 00:00:00",
                        "count": 0.0,
                        "mean": 0.0,
                        "std": 0.0,
                        "min": 0.0,
                        "25%": 0.0,
                        "50%": 0.0,
                        "75%": 0.0,
                        "max": 0.0
                    },
                    {
                        "datetime": "2022-10-01 00:00:00",
                        "count": 0.0,
                        "mean": 0.0,
                        "std": 0.0,
                        "min": 0.0,
                        "25%": 0.0,
                        "50%": 0.0,
                        "75%": 0.0,
                        "max": 0.0
                    },
                    {
                        "datetime": "2022-10-15 00:00:00",
                        "count": 0.0,
                        "mean": 0.0,
                        "std": 0.0,
                        "min": 0.0,
                        "25%": 0.0,
                        "50%": 0.0,
                        "75%": 0.0,
                        "max": 0.0
                    },
                    {
                        "datetime": "2022-10-29 00:00:00",
                        "count": 0.0,
                        "mean": 0.0,
                        "std": 0.0,
                        "min": 0.0,
                        "25%": 0.0,
                        "50%": 0.0,
                        "75%": 0.0,
                        "max": 0.0
                    },
                    {
                        "datetime": "2022-11-12 00:00:00",
                        "count": 573.0,
                        "mean": 46.596858638743456,
                        "std": 15.067672194448376,
                        "min": 20.0,
                        "25%": 50.0,
                        "50%": 50.0,
                        "75%": 50.0,
                        "max": 150.0
                    },
                    {
                        "datetime": "2022-11-26 00:00:00",
                        "count": 5.0,
                        "mean": 0.0294389391112162,
                        "std": -0.06211110648257012,
                        "min": 0.0,
                        "25%": 0.0,
                        "50%": 0.0,
                        "75%": 0.0,
                        "max": 0.0
                    }
                ]
            }
        },
        "OneYear": {
            "archive": {
                "count": 0,
                "data": []
            },
            "diff": {
                "count": 0,
                "data": []
            }
        }
    },
    "calc": {
        "latest_date": "2022-11-26 00:00:00",
        "updated_at": "2022-11-26 20:09:16"
    }
}