{
    "price": {
        "current": {
            "datetime": "2022-12-24 00:00:00",
            "count": 258.0,
            "mean": 767.9457364341085,
            "std": 28.22996450844672,
            "min": 500.0,
            "25%": 780.0,
            "50%": 780.0,
            "75%": 780.0,
            "max": 800.0
        },
        "summary7Days": {
            "datetime": "2022-12-24 00:00:00",
            "count": -41.0,
            "mean": -2.489046174587088,
            "std": 2.1658026942478266,
            "min": 0.0,
            "25%": 0.0,
            "50%": 0.0,
            "75%": 0.0,
            "max": 0.0
        },
        "volatility": {
            "weekly": {
                "min": {
                    "basePrice": 500.0,
                    "latestPrice": 500.0,
                    "percent": 0.0
                },
                "50%": {
                    "basePrice": 780.0,
                    "latestPrice": 780.0,
                    "percent": 0.0
                }
            },
            "daily": {
                "min": {
                    "basePrice": 500.0,
                    "latestPrice": 500.0,
                    "percent": 0.0
                },
                "50%": {
                    "basePrice": 780.0,
                    "latestPrice": 780.0,
                    "percent": 0.0
                }
            }
        },
        "weekly": {
            "archive": {
                "count": 7,
                "data": [
                    {
                        "datetime": "2022-12-18 00:00:00",
                        "count": 299.0,
                        "mean": 770.4347826086956,
                        "std": 26.064161814198894,
                        "min": 500.0,
                        "25%": 780.0,
                        "50%": 780.0,
                        "75%": 780.0,
                        "max": 800.0
                    },
                    {
                        "datetime": "2022-12-19 00:00:00",
                        "count": 299.0,
                        "mean": 770.4347826086956,
                        "std": 26.064161814198894,
                        "min": 500.0,
                        "25%": 780.0,
                        "50%": 780.0,
                        "75%": 780.0,
                        "max": 800.0
                    },
                    {
                        "datetime": "2022-12-20 00:00:00",
                        "count": 303.0,
                        "mean": 769.9009900990098,
                        "std": 26.30041860663072,
                        "min": 500.0,
                        "25%": 780.0,
                        "50%": 780.0,
                        "75%": 780.0,
                        "max": 800.0
                    },
                    {
                        "datetime": "2022-12-21 00:00:00",
                        "count": 303.0,
                        "mean": 769.9009900990098,
                        "std": 26.30041860663072,
                        "min": 500.0,
                        "25%": 780.0,
                        "50%": 780.0,
                        "75%": 780.0,
                        "max": 800.0
                    },
                    {
                        "datetime": "2022-12-22 00:00:00",
                        "count": 298.0,
                        "mean": 769.5637583892617,
                        "std": 26.58087769859421,
                        "min": 500.0,
                        "25%": 780.0,
                        "50%": 780.0,
                        "75%": 780.0,
                        "max": 800.0
                    },
                    {
                        "datetime": "2022-12-23 00:00:00",
                        "count": 277.0,
                        "mean": 768.9530685920578,
                        "std": 27.319658334094427,
                        "min": 500.0,
                        "25%": 780.0,
                        "50%": 780.0,
                        "75%": 780.0,
                        "max": 800.0
                    },
                    {
                        "datetime": "2022-12-24 00:00:00",
                        "count": 258.0,
                        "mean": 767.9457364341085,
                        "std": 28.22996450844672,
                        "min": 500.0,
                        "25%": 780.0,
                        "50%": 780.0,
                        "75%": 780.0,
                        "max": 800.0
                    }
                ]
            },
            "diff": {
                "count": 7,
                "data": [
                    {
                        "datetime": "2022-12-18 00:00:00",
                        "count": null,
                        "mean": null,
                        "std": null,
                        "min": null,
                        "25%": null,
                        "50%": null,
                        "75%": null,
                        "max": null
                    },
                    {
                        "datetime": "2022-12-19 00:00:00",
                        "count": 0.0,
                        "mean": 0.0,
                        "std": 0.0,
                        "min": 0.0,
                        "25%": 0.0,
                        "50%": 0.0,
                        "75%": 0.0,
                        "max": 0.0
                    },
                    {
                        "datetime": "2022-12-20 00:00:00",
                        "count": 4.0,
                        "mean": -0.5337925096857816,
                        "std": 0.23625679243182773,
                        "min": 0.0,
                        "25%": 0.0,
                        "50%": 0.0,
                        "75%": 0.0,
                        "max": 0.0
                    },
                    {
                        "datetime": "2022-12-21 00:00:00",
                        "count": 0.0,
                        "mean": 0.0,
                        "std": 0.0,
                        "min": 0.0,
                        "25%": 0.0,
                        "50%": 0.0,
                        "75%": 0.0,
                        "max": 0.0
                    },
                    {
                        "datetime": "2022-12-22 00:00:00",
                        "count": -5.0,
                        "mean": -0.33723170974815275,
                        "std": 0.2804590919634897,
                        "min": 0.0,
                        "25%": 0.0,
                        "50%": 0.0,
                        "75%": 0.0,
                        "max": 0.0
                    },
                    {
                        "datetime": "2022-12-23 00:00:00",
                        "count": -21.0,
                        "mean": -0.6106897972039178,
                        "std": 0.7387806355002162,
                        "min": 0.0,
                        "25%": 0.0,
                        "50%": 0.0,
                        "75%": 0.0,
                        "max": 0.0
                    },
                    {
                        "datetime": "2022-12-24 00:00:00",
                        "count": -19.0,
                        "mean": -1.0073321579492358,
                        "std": 0.9103061743522929,
                        "min": 0.0,
                        "25%": 0.0,
                        "50%": 0.0,
                        "75%": 0.0,
                        "max": 0.0
                    }
                ]
            }
        },
        "halfYear": {
            "archive": {
                "count": 13,
                "data": [
                    {
                        "datetime": "2022-07-09 00:00:00",
                        "count": 0.0,
                        "mean": 0.0,
                        "std": 0.0,
                        "min": 0.0,
                        "25%": 0.0,
                        "50%": 0.0,
                        "75%": 0.0,
                        "max": 0.0
                    },
                    {
                        "datetime": "2022-07-23 00:00:00",
                        "count": 0.0,
                        "mean": 0.0,
                        "std": 0.0,
                        "min": 0.0,
                        "25%": 0.0,
                        "50%": 0.0,
                        "75%": 0.0,
                        "max": 0.0
                    },
                    {
                        "datetime": "2022-08-06 00:00:00",
                        "count": 0.0,
                        "mean": 0.0,
                        "std": 0.0,
                        "min": 0.0,
                        "25%": 0.0,
                        "50%": 0.0,
                        "75%": 0.0,
                        "max": 0.0
                    },
                    {
                        "datetime": "2022-08-20 00:00:00",
                        "count": 0.0,
                        "mean": 0.0,
                        "std": 0.0,
                        "min": 0.0,
                        "25%": 0.0,
                        "50%": 0.0,
                        "75%": 0.0,
                        "max": 0.0
                    },
                    {
                        "datetime": "2022-09-03 00:00:00",
                        "count": 0.0,
                        "mean": 0.0,
                        "std": 0.0,
                        "min": 0.0,
                        "25%": 0.0,
                        "50%": 0.0,
                        "75%": 0.0,
                        "max": 0.0
                    },
                    {
                        "datetime": "2022-09-17 00:00:00",
                        "count": 64.0,
                        "mean": 595.625,
                        "std": 43.7117179451264,
                        "min": 500.0,
                        "25%": 580.0,
                        "50%": 580.0,
                        "75%": 580.0,
                        "max": 700.0
                    },
                    {
                        "datetime": "2022-10-01 00:00:00",
                        "count": 87.0,
                        "mean": 582.6436781609195,
                        "std": 39.69241536460852,
                        "min": 500.0,
                        "25%": 580.0,
                        "50%": 580.0,
                        "75%": 580.0,
                        "max": 700.0
                    },
                    {
                        "datetime": "2022-10-15 00:00:00",
                        "count": 20.0,
                        "mean": 663.0,
                        "std": 82.85053123737825,
                        "min": 430.0,
                        "25%": 700.0,
                        "50%": 700.0,
                        "75%": 700.0,
                        "max": 700.0
                    },
                    {
                        "datetime": "2022-10-29 00:00:00",
                        "count": 59.0,
                        "mean": 751.5254237288135,
                        "std": 48.52349446302858,
                        "min": 500.0,
                        "25%": 700.0,
                        "50%": 780.0,
                        "75%": 780.0,
                        "max": 780.0
                    },
                    {
                        "datetime": "2022-11-12 00:00:00",
                        "count": 100.0,
                        "mean": 747.7,
                        "std": 55.73847663668049,
                        "min": 480.0,
                        "25%": 730.0,
                        "50%": 780.0,
                        "75%": 780.0,
                        "max": 780.0
                    },
                    {
                        "datetime": "2022-11-26 00:00:00",
                        "count": 258.0,
                        "mean": 769.6124031007752,
                        "std": 31.28637900004016,
                        "min": 500.0,
                        "25%": 780.0,
                        "50%": 780.0,
                        "75%": 780.0,
                        "max": 800.0
                    },
                    {
                        "datetime": "2022-12-10 00:00:00",
                        "count": 224.0,
                        "mean": 769.1517857142857,
                        "std": 30.726541548656584,
                        "min": 500.0,
                        "25%": 780.0,
                        "50%": 780.0,
                        "75%": 780.0,
                        "max": 800.0
                    },
                    {
                        "datetime": "2022-12-24 00:00:00",
                        "count": 258.0,
                        "mean": 767.9457364341085,
                        "std": 28.22996450844672,
                        "min": 500.0,
                        "25%": 780.0,
                        "50%": 780.0,
                        "75%": 780.0,
                        "max": 800.0
                    }
                ]
            },
            "diff": {
                "count": 13,
                "data": [
                    {
                        "datetime": "2022-07-09 00:00:00",
                        "count": null,
                        "mean": null,
                        "std": null,
                        "min": null,
                        "25%": null,
                        "50%": null,
                        "75%": null,
                        "max": null
                    },
                    {
                        "datetime": "2022-07-23 00:00:00",
                        "count": 0.0,
                        "mean": 0.0,
                        "std": 0.0,
                        "min": 0.0,
                        "25%": 0.0,
                        "50%": 0.0,
                        "75%": 0.0,
                        "max": 0.0
                    },
                    {
                        "datetime": "2022-08-06 00:00:00",
                        "count": 0.0,
                        "mean": 0.0,
                        "std": 0.0,
                        "min": 0.0,
                        "25%": 0.0,
                        "50%": 0.0,
                        "75%": 0.0,
                        "max": 0.0
                    },
                    {
                        "datetime": "2022-08-20 00:00:00",
                        "count": 0.0,
                        "mean": 0.0,
                        "std": 0.0,
                        "min": 0.0,
                        "25%": 0.0,
                        "50%": 0.0,
                        "75%": 0.0,
                        "max": 0.0
                    },
                    {
                        "datetime": "2022-09-03 00:00:00",
                        "count": 0.0,
                        "mean": 0.0,
                        "std": 0.0,
                        "min": 0.0,
                        "25%": 0.0,
                        "50%": 0.0,
                        "75%": 0.0,
                        "max": 0.0
                    },
                    {
                        "datetime": "2022-09-17 00:00:00",
                        "count": 64.0,
                        "mean": 595.625,
                        "std": 43.7117179451264,
                        "min": 500.0,
                        "25%": 580.0,
                        "50%": 580.0,
                        "75%": 580.0,
                        "max": 700.0
                    },
                    {
                        "datetime": "2022-10-01 00:00:00",
                        "count": 23.0,
                        "mean": -12.981321839080465,
                        "std": -4.019302580517881,
                        "min": 0.0,
                        "25%": 0.0,
                        "50%": 0.0,
                        "75%": 0.0,
                        "max": 0.0
                    },
                    {
                        "datetime": "2022-10-15 00:00:00",
                        "count": -67.0,
                        "mean": 80.35632183908046,
                        "std": 43.15811587276973,
                        "min": -70.0,
                        "25%": 120.0,
                        "50%": 120.0,
                        "75%": 120.0,
                        "max": 0.0
                    },
                    {
                        "datetime": "2022-10-29 00:00:00",
                        "count": 39.0,
                        "mean": 88.52542372881351,
                        "std": -34.32703677434967,
                        "min": 70.0,
                        "25%": 0.0,
                        "50%": 80.0,
                        "75%": 80.0,
                        "max": 80.0
                    },
                    {
                        "datetime": "2022-11-12 00:00:00",
                        "count": 41.0,
                        "mean": -3.825423728813462,
                        "std": 7.2149821736519115,
                        "min": -20.0,
                        "25%": 30.0,
                        "50%": 0.0,
                        "75%": 0.0,
                        "max": 0.0
                    },
                    {
                        "datetime": "2022-11-26 00:00:00",
                        "count": 158.0,
                        "mean": 21.912403100775123,
                        "std": -24.452097636640328,
                        "min": 20.0,
                        "25%": 50.0,
                        "50%": 0.0,
                        "75%": 0.0,
                        "max": 20.0
                    },
                    {
                        "datetime": "2022-12-10 00:00:00",
                        "count": -34.0,
                        "mean": -0.4606173864895027,
                        "std": -0.5598374513835758,
                        "min": 0.0,
                        "25%": 0.0,
                        "50%": 0.0,
                        "75%": 0.0,
                        "max": 0.0
                    },
                    {
                        "datetime": "2022-12-24 00:00:00",
                        "count": 34.0,
                        "mean": -1.206049280177126,
                        "std": -2.496577040209864,
                        "min": 0.0,
                        "25%": 0.0,
                        "50%": 0.0,
                        "75%": 0.0,
                        "max": 0.0
                    }
                ]
            }
        },
        "OneYear": {
            "archive": {
                "count": 0,
                "data": []
            },
            "diff": {
                "count": 0,
                "data": []
            }
        }
    },
    "calc": {
        "latest_date": "2022-12-24 00:00:00",
        "updated_at": "2022-12-24 20:08:08"
    }
}