{
    "price": {
        "current": {
            "datetime": "2022-12-26 00:00:00",
            "count": 94.0,
            "mean": 1050.2446808510638,
            "std": 78.83925202317985,
            "min": 650.0,
            "25%": 1080.0,
            "50%": 1080.0,
            "75%": 1080.0,
            "max": 1080.0
        },
        "summary7Days": {
            "datetime": "2022-12-26 00:00:00",
            "count": 35.0,
            "mean": 83.24468085106378,
            "std": -16.916183583765502,
            "min": -100.0,
            "25%": 100.0,
            "50%": 100.0,
            "75%": 100.0,
            "max": -420.0
        },
        "volatility": {
            "weekly": {
                "min": {
                    "basePrice": 750.0,
                    "latestPrice": 650.0,
                    "percent": -13.33
                },
                "50%": {
                    "basePrice": 980.0,
                    "latestPrice": 1080.0,
                    "percent": 10.2
                }
            },
            "daily": {
                "min": {
                    "basePrice": 650.0,
                    "latestPrice": 650.0,
                    "percent": 0.0
                },
                "50%": {
                    "basePrice": 1080.0,
                    "latestPrice": 1080.0,
                    "percent": 0.0
                }
            }
        },
        "weekly": {
            "archive": {
                "count": 7,
                "data": [
                    {
                        "datetime": "2022-12-20 00:00:00",
                        "count": 59.0,
                        "mean": 967.0,
                        "std": 95.75543560694535,
                        "min": 750.0,
                        "25%": 980.0,
                        "50%": 980.0,
                        "75%": 980.0,
                        "max": 1500.0
                    },
                    {
                        "datetime": "2022-12-21 00:00:00",
                        "count": 55.0,
                        "mean": 957.5090909090908,
                        "std": 72.01565486374852,
                        "min": 750.0,
                        "25%": 980.0,
                        "50%": 980.0,
                        "75%": 980.0,
                        "max": 1200.0
                    },
                    {
                        "datetime": "2022-12-22 00:00:00",
                        "count": 59.0,
                        "mean": 959.0338983050848,
                        "std": 69.7216055421043,
                        "min": 750.0,
                        "25%": 980.0,
                        "50%": 980.0,
                        "75%": 980.0,
                        "max": 1200.0
                    },
                    {
                        "datetime": "2022-12-23 00:00:00",
                        "count": 18.0,
                        "mean": 911.2777777777778,
                        "std": 114.49880839634535,
                        "min": 750.0,
                        "25%": 804.25,
                        "50%": 915.0,
                        "75%": 980.0,
                        "max": 1200.0
                    },
                    {
                        "datetime": "2022-12-24 00:00:00",
                        "count": 51.0,
                        "mean": 1027.313725490196,
                        "std": 105.07244932827604,
                        "min": 650.0,
                        "25%": 990.0,
                        "50%": 1080.0,
                        "75%": 1080.0,
                        "max": 1200.0
                    },
                    {
                        "datetime": "2022-12-25 00:00:00",
                        "count": 67.0,
                        "mean": 1037.2089552238806,
                        "std": 94.31548240675639,
                        "min": 650.0,
                        "25%": 1080.0,
                        "50%": 1080.0,
                        "75%": 1080.0,
                        "max": 1200.0
                    },
                    {
                        "datetime": "2022-12-26 00:00:00",
                        "count": 94.0,
                        "mean": 1050.2446808510638,
                        "std": 78.83925202317985,
                        "min": 650.0,
                        "25%": 1080.0,
                        "50%": 1080.0,
                        "75%": 1080.0,
                        "max": 1080.0
                    }
                ]
            },
            "diff": {
                "count": 7,
                "data": [
                    {
                        "datetime": "2022-12-20 00:00:00",
                        "count": null,
                        "mean": null,
                        "std": null,
                        "min": null,
                        "25%": null,
                        "50%": null,
                        "75%": null,
                        "max": null
                    },
                    {
                        "datetime": "2022-12-21 00:00:00",
                        "count": -4.0,
                        "mean": -9.490909090909213,
                        "std": -23.73978074319683,
                        "min": 0.0,
                        "25%": 0.0,
                        "50%": 0.0,
                        "75%": 0.0,
                        "max": -300.0
                    },
                    {
                        "datetime": "2022-12-22 00:00:00",
                        "count": 4.0,
                        "mean": 1.524807395994003,
                        "std": -2.2940493216442235,
                        "min": 0.0,
                        "25%": 0.0,
                        "50%": 0.0,
                        "75%": 0.0,
                        "max": 0.0
                    },
                    {
                        "datetime": "2022-12-23 00:00:00",
                        "count": -41.0,
                        "mean": -47.75612052730696,
                        "std": 44.777202854241054,
                        "min": 0.0,
                        "25%": -175.75,
                        "50%": -65.0,
                        "75%": 0.0,
                        "max": 0.0
                    },
                    {
                        "datetime": "2022-12-24 00:00:00",
                        "count": 33.0,
                        "mean": 116.03594771241819,
                        "std": -9.426359068069317,
                        "min": -100.0,
                        "25%": 185.75,
                        "50%": 165.0,
                        "75%": 100.0,
                        "max": 0.0
                    },
                    {
                        "datetime": "2022-12-25 00:00:00",
                        "count": 16.0,
                        "mean": 9.895229733684573,
                        "std": -10.756966921519648,
                        "min": 0.0,
                        "25%": 90.0,
                        "50%": 0.0,
                        "75%": 0.0,
                        "max": 0.0
                    },
                    {
                        "datetime": "2022-12-26 00:00:00",
                        "count": 27.0,
                        "mean": 13.035725627183183,
                        "std": -15.476230383576535,
                        "min": 0.0,
                        "25%": 0.0,
                        "50%": 0.0,
                        "75%": 0.0,
                        "max": -120.0
                    }
                ]
            }
        },
        "halfYear": {
            "archive": {
                "count": 13,
                "data": [
                    {
                        "datetime": "2022-07-11 00:00:00",
                        "count": 0.0,
                        "mean": 0.0,
                        "std": 0.0,
                        "min": 0.0,
                        "25%": 0.0,
                        "50%": 0.0,
                        "75%": 0.0,
                        "max": 0.0
                    },
                    {
                        "datetime": "2022-07-25 00:00:00",
                        "count": 0.0,
                        "mean": 0.0,
                        "std": 0.0,
                        "min": 0.0,
                        "25%": 0.0,
                        "50%": 0.0,
                        "75%": 0.0,
                        "max": 0.0
                    },
                    {
                        "datetime": "2022-08-08 00:00:00",
                        "count": 0.0,
                        "mean": 0.0,
                        "std": 0.0,
                        "min": 0.0,
                        "25%": 0.0,
                        "50%": 0.0,
                        "75%": 0.0,
                        "max": 0.0
                    },
                    {
                        "datetime": "2022-08-22 00:00:00",
                        "count": 0.0,
                        "mean": 0.0,
                        "std": 0.0,
                        "min": 0.0,
                        "25%": 0.0,
                        "50%": 0.0,
                        "75%": 0.0,
                        "max": 0.0
                    },
                    {
                        "datetime": "2022-09-05 00:00:00",
                        "count": 0.0,
                        "mean": 0.0,
                        "std": 0.0,
                        "min": 0.0,
                        "25%": 0.0,
                        "50%": 0.0,
                        "75%": 0.0,
                        "max": 0.0
                    },
                    {
                        "datetime": "2022-09-19 00:00:00",
                        "count": 0.0,
                        "mean": 0.0,
                        "std": 0.0,
                        "min": 0.0,
                        "25%": 0.0,
                        "50%": 0.0,
                        "75%": 0.0,
                        "max": 0.0
                    },
                    {
                        "datetime": "2022-10-03 00:00:00",
                        "count": 0.0,
                        "mean": 0.0,
                        "std": 0.0,
                        "min": 0.0,
                        "25%": 0.0,
                        "50%": 0.0,
                        "75%": 0.0,
                        "max": 0.0
                    },
                    {
                        "datetime": "2022-10-17 00:00:00",
                        "count": 0.0,
                        "mean": 0.0,
                        "std": 0.0,
                        "min": 0.0,
                        "25%": 0.0,
                        "50%": 0.0,
                        "75%": 0.0,
                        "max": 0.0
                    },
                    {
                        "datetime": "2022-10-31 00:00:00",
                        "count": 0.0,
                        "mean": 0.0,
                        "std": 0.0,
                        "min": 0.0,
                        "25%": 0.0,
                        "50%": 0.0,
                        "75%": 0.0,
                        "max": 0.0
                    },
                    {
                        "datetime": "2022-11-14 00:00:00",
                        "count": 0.0,
                        "mean": 0.0,
                        "std": 0.0,
                        "min": 0.0,
                        "25%": 0.0,
                        "50%": 0.0,
                        "75%": 0.0,
                        "max": 0.0
                    },
                    {
                        "datetime": "2022-11-28 00:00:00",
                        "count": 0.0,
                        "mean": 0.0,
                        "std": 0.0,
                        "min": 0.0,
                        "25%": 0.0,
                        "50%": 0.0,
                        "75%": 0.0,
                        "max": 0.0
                    },
                    {
                        "datetime": "2022-12-12 00:00:00",
                        "count": 53.0,
                        "mean": 893.8867924528302,
                        "std": 91.52020802015392,
                        "min": 800.0,
                        "25%": 880.0,
                        "50%": 880.0,
                        "75%": 880.0,
                        "max": 1500.0
                    },
                    {
                        "datetime": "2022-12-26 00:00:00",
                        "count": 94.0,
                        "mean": 1050.2446808510638,
                        "std": 78.83925202317985,
                        "min": 650.0,
                        "25%": 1080.0,
                        "50%": 1080.0,
                        "75%": 1080.0,
                        "max": 1080.0
                    }
                ]
            },
            "diff": {
                "count": 13,
                "data": [
                    {
                        "datetime": "2022-07-11 00:00:00",
                        "count": null,
                        "mean": null,
                        "std": null,
                        "min": null,
                        "25%": null,
                        "50%": null,
                        "75%": null,
                        "max": null
                    },
                    {
                        "datetime": "2022-07-25 00:00:00",
                        "count": 0.0,
                        "mean": 0.0,
                        "std": 0.0,
                        "min": 0.0,
                        "25%": 0.0,
                        "50%": 0.0,
                        "75%": 0.0,
                        "max": 0.0
                    },
                    {
                        "datetime": "2022-08-08 00:00:00",
                        "count": 0.0,
                        "mean": 0.0,
                        "std": 0.0,
                        "min": 0.0,
                        "25%": 0.0,
                        "50%": 0.0,
                        "75%": 0.0,
                        "max": 0.0
                    },
                    {
                        "datetime": "2022-08-22 00:00:00",
                        "count": 0.0,
                        "mean": 0.0,
                        "std": 0.0,
                        "min": 0.0,
                        "25%": 0.0,
                        "50%": 0.0,
                        "75%": 0.0,
                        "max": 0.0
                    },
                    {
                        "datetime": "2022-09-05 00:00:00",
                        "count": 0.0,
                        "mean": 0.0,
                        "std": 0.0,
                        "min": 0.0,
                        "25%": 0.0,
                        "50%": 0.0,
                        "75%": 0.0,
                        "max": 0.0
                    },
                    {
                        "datetime": "2022-09-19 00:00:00",
                        "count": 0.0,
                        "mean": 0.0,
                        "std": 0.0,
                        "min": 0.0,
                        "25%": 0.0,
                        "50%": 0.0,
                        "75%": 0.0,
                        "max": 0.0
                    },
                    {
                        "datetime": "2022-10-03 00:00:00",
                        "count": 0.0,
                        "mean": 0.0,
                        "std": 0.0,
                        "min": 0.0,
                        "25%": 0.0,
                        "50%": 0.0,
                        "75%": 0.0,
                        "max": 0.0
                    },
                    {
                        "datetime": "2022-10-17 00:00:00",
                        "count": 0.0,
                        "mean": 0.0,
                        "std": 0.0,
                        "min": 0.0,
                        "25%": 0.0,
                        "50%": 0.0,
                        "75%": 0.0,
                        "max": 0.0
                    },
                    {
                        "datetime": "2022-10-31 00:00:00",
                        "count": 0.0,
                        "mean": 0.0,
                        "std": 0.0,
                        "min": 0.0,
                        "25%": 0.0,
                        "50%": 0.0,
                        "75%": 0.0,
                        "max": 0.0
                    },
                    {
                        "datetime": "2022-11-14 00:00:00",
                        "count": 0.0,
                        "mean": 0.0,
                        "std": 0.0,
                        "min": 0.0,
                        "25%": 0.0,
                        "50%": 0.0,
                        "75%": 0.0,
                        "max": 0.0
                    },
                    {
                        "datetime": "2022-11-28 00:00:00",
                        "count": 0.0,
                        "mean": 0.0,
                        "std": 0.0,
                        "min": 0.0,
                        "25%": 0.0,
                        "50%": 0.0,
                        "75%": 0.0,
                        "max": 0.0
                    },
                    {
                        "datetime": "2022-12-12 00:00:00",
                        "count": 53.0,
                        "mean": 893.8867924528302,
                        "std": 91.52020802015392,
                        "min": 800.0,
                        "25%": 880.0,
                        "50%": 880.0,
                        "75%": 880.0,
                        "max": 1500.0
                    },
                    {
                        "datetime": "2022-12-26 00:00:00",
                        "count": 41.0,
                        "mean": 156.35788839823363,
                        "std": -12.680955996974063,
                        "min": -150.0,
                        "25%": 200.0,
                        "50%": 200.0,
                        "75%": 200.0,
                        "max": -420.0
                    }
                ]
            }
        },
        "OneYear": {
            "archive": {
                "count": 0,
                "data": []
            },
            "diff": {
                "count": 0,
                "data": []
            }
        }
    },
    "calc": {
        "latest_date": "2022-12-26 00:00:00",
        "updated_at": "2022-12-26 20:09:54"
    }
}